Parser/__init__.py
Parser/DrugBank/DrugBankParser.py
Parser/DrugBank/__init__.py
Parser/PDB/PDBParser.py
Parser/PDB/__init__.py
core/LigandPrep.py
core/MMPBSA.py
core/TLEaP.py
core/__init__.py
core/parmed.py
core/pdb4amber.py
core/pmemd.py
PyDanamics-0.0.0.dist-info/METADATA
PyDanamics-0.0.0.dist-info/WHEEL
PyDanamics-0.0.0.dist-info/top_level.txt
PyDanamics-0.0.0.dist-info/RECORD
