Metadata-Version: 2.1
Name: PyDanamics
Version: 0.0.0
Summary: Molecular dynamic simulation assistant for beginners
Home-page: https://github.com/pertinency/PyDynamics
License: UNKNOWN
Download-URL: https://github.com/pertinency/PyDynamics/archive/master.zip
Keywords: molecular dynamics,simulation,Amber
Platform: UNKNOWN
Classifier: Programming Language :: Python :: 3
Classifier: Programming Language :: Python :: 3.2
Classifier: Programming Language :: Python :: 3.3
Classifier: Programming Language :: Python :: 3.4
Classifier: Programming Language :: Python :: 3.5
Classifier: Programming Language :: Python :: 3.6
Requires-Python: >=3
